amlpp/__init__.py
amlpp/additional/__init__.py
amlpp/additional/metrics.py
amlpp/additional/progress_bar.py
amlpp/additional/storytelling.py
amlpp/architect/__init__.py
amlpp/architect/experimenter.py
amlpp/architect/projecter.py
amlpp/conveyor/__init__.py
amlpp/conveyor/conveyor.py
amlpp/fit_model/__init__.py
amlpp/fit_model/model_params.py
amlpp/fit_model/optimizers.py
amlpp/fit_model/preprocessors_params.py
amlpp/transformers/__init__.py
amlpp/transformers/_base_transform.py
amlpp/transformers/categorical.py
amlpp/transformers/imputers.py
amlpp/transformers/word_embeddings.py
amlpp-0.1.9.7.dist-info/LICENSE
amlpp-0.1.9.7.dist-info/METADATA
amlpp-0.1.9.7.dist-info/WHEEL
amlpp-0.1.9.7.dist-info/top_level.txt
amlpp-0.1.9.7.dist-info/RECORD
