Metadata-Version: 2.1
Name: amlpp
Version: 0.1.9.7
Summary: Wrapper for ml library
Home-page: https://github.com/Asirg/amlpp
Author: Asir Muminov
Author-email: vojt.tieg295i@gmail.com
License: UNKNOWN
Platform: UNKNOWN
Classifier: Programming Language :: Python :: 3
Classifier: License :: OSI Approved :: MIT License
Classifier: Operating System :: OS Independent
Requires-Python: >=3.0
License-File: LICENSE
Requires-Dist: scikit-learn
Requires-Dist: matplotlib
Requires-Dist: pymorphy2
Requires-Dist: lightgbm
Requires-Dist: catboost
Requires-Dist: xgboost
Requires-Dist: typing
Requires-Dist: gensim
Requires-Dist: optuna
Requires-Dist: numpy
Requires-Dist: shap
Requires-Dist: TPOT
Requires-Dist: tqdm
Requires-Dist: nltk
